redco/__init__.py
redco/deployers/__init__.py
redco/deployers/ckpt_utils.py
redco/deployers/data_utils.py
redco/deployers/deployer.py
redco/deployers/log_utils.py
redco/deployers/opt_utils.py
redco/deployers/partition_utils.py
redco/predictors/__init__.py
redco/predictors/predictor.py
redco/predictors/utils.py
redco/trainers/__init__.py
redco/trainers/trainer.py
redco/trainers/utils.py
redco-0.4.23.dist-info/LICENSE
redco-0.4.23.dist-info/METADATA
redco-0.4.23.dist-info/WHEEL
redco-0.4.23.dist-info/top_level.txt
redco-0.4.23.dist-info/RECORD
