Metadata-Version: 2.1
Name: redco
Version: 0.4.23
Home-page: https://github.com/tanyuqian/redco
Author: Bowen Tan
Requires-Python: >=3.8
License-File: LICENSE
Requires-Dist: jax
Requires-Dist: flax
Requires-Dist: optax
